{
    "final_decision":  "PASS",
    "reason_for_decision":  "The article clears the pass bar by focusing on integration as a workflow problem involving role separation, timing, coordinate alignment, and operator closure.",
    "overall_score":  8.6,
    "word_count":  1089,
    "dimension_scores":  {
                             "structure_logical_clarity":  9,
                             "target_classification_content_framing":  9,
                             "marketing_noise_control":  9,
                             "content_depth":  9,
                             "readability_human_quality":  8,
                             "information_density":  8,
                             "seo_knowledge_base_fitness":  9,
                             "technical_credibility":  8,
                             "decision_value":  9,
                             "original_insight":  8
                         },
    "failed_dimensions_below_5":  [

                                  ],
    "ai_signals_detected":  [

                            ],
    "major_issues":  [

                     ],
    "revision_actions":  [

                         ],
    "rewrite_actions":  [

                        ],
    "strengths":  [
                      "The article explains that shared networking is not the same as real integration, which is the right architectural starting point.",
                      "Its treatment of time synchronization, coordinate registration, and confidence logic is especially strong.",
                      "The operator-closure and degraded-mode sections make the guidance practical rather than theoretical."
                  ],
    "summary_assessment":  "This article passes comfortably. It is one of the stronger system-design pieces in the queue because it treats fusion as an operational chain instead of a generic feature."
}